App/Validation/__init__.py
App/Validation/automation.py
App/Validation/Automation/__init__.py
App/Validation/Automation/alarming.py
App/Validation/Automation/purging.py
App/Validation/Automation/unix.py
App/Validation/Automation/web.py
AppValidationAutomation.egg-info/PKG-INFO
AppValidationAutomation.egg-info/SOURCES.txt
AppValidationAutomation.egg-info/dependency_links.txt
AppValidationAutomation.egg-info/top_level.txt
bin/app_validation.py