Metadata-Version: 1.0
Name: AppValidationAutomation
Version: 0.1
Summary: Automation Framework - Web and Unix Centric Apps
Home-page: http://pypi.python.org/pypi/AppValidationAutomation/0.1
Author: Varun Juyal
Author-email: varunjuyal123@yahoo.com
License: UNKNOWN
Platform: UNKNOWN
